sing_box_config/__init__.py
sing_box_config/export.py
sing_box_config/main.py
sing_box_config/parser/__init__.py
sing_box_config/parser/base.py
sing_box_config/parser/shadowsocks.py
sing_box_config/parser/sing_box.py
sing_box_config-0.8.0.dist-info/METADATA
sing_box_config-0.8.0.dist-info/WHEEL
sing_box_config-0.8.0.dist-info/entry_points.txt
sing_box_config-0.8.0.dist-info/licenses/LICENSE
sing_box_config-0.8.0.dist-info/RECORD
