Metadata-Version: 2.4
Name: sing-box-config
Version: 0.8.0
Summary: Yet another configuration generator for sing-box
Project-URL: Homepage, https://github.com/ak1ra-lab/sing-box-tproxy
Project-URL: Changelog, https://github.com/ak1ra-lab/sing-box-tproxy/blob/master/CHANGELOG.md
Author-email: ak1ra <git@ak1ra.xyz>
License-Expression: MIT
License-File: LICENSE
Keywords: ansible,sing-box,tproxy
Classifier: Development Status :: 4 - Beta
Classifier: Environment :: Console
Classifier: Intended Audience :: System Administrators
Classifier: Operating System :: OS Independent
Classifier: Programming Language :: Python :: 3
Classifier: Programming Language :: Python :: 3 :: Only
Classifier: Programming Language :: Python :: 3.11
Classifier: Programming Language :: Python :: 3.12
Classifier: Programming Language :: Python :: 3.13
Requires-Python: >=3.11
Requires-Dist: argcomplete>=3.6.2
Requires-Dist: chaos-utils>=0.3.1
Requires-Dist: httpx>=0.28.1
Requires-Dist: tenacity>=9.1.2
